cloudstate/__init__.py
cloudstate/cloudstate.py
cloudstate/contexts.py
cloudstate/discovery_servicer.py
cloudstate/entity_key_pb2.py
cloudstate/entity_key_pb2_grpc.py
cloudstate/entity_pb2.py
cloudstate/entity_pb2_grpc.py
cloudstate/evensourced_servicer.py
cloudstate/event_sourced_context.py
cloudstate/event_sourced_entity.py
cloudstate/event_sourced_pb2.py
cloudstate/event_sourced_pb2_grpc.py
cloudstate/version.py
cloudstate-0.1.1.dist-info/LICENSE
cloudstate-0.1.1.dist-info/METADATA
cloudstate-0.1.1.dist-info/WHEEL
cloudstate-0.1.1.dist-info/top_level.txt
cloudstate-0.1.1.dist-info/RECORD
