Metadata-Version: 2.1
Name: cloudstate
Version: 0.1.1
Summary: Cloudstate Python Support Library
Home-page: https://github.com/cloudstateio/python-support
Author: Cloudstate
License: Apache 2.0
Project-URL: Documentation, https://cloudstate.io/docs/user/lang/index.html
Project-URL: Source, https://github.com/cloudstateio/python-support
Platform: UNKNOWN
Classifier: Intended Audience :: Developers
Classifier: License :: OSI Approved :: Apache Software License
Classifier: Operating System :: OS Independent
Classifier: Programming Language :: Python
Classifier: Programming Language :: Python :: 3.6
Requires-Python: >=3.6
Requires-Dist: protobuf (==3.11.3)
Requires-Dist: google-api (==0.1.12)
Requires-Dist: grpcio (==1.28.1)
Requires-Dist: grpcio-tools (==1.28.1)
Requires-Dist: attrs (==19.3.0)
Requires-Dist: googleapis-common-protos (>=1.51.0)
